{"8": {"initiate_commands": [["npm", "install"], ["node", "server.js"]], "requirements": ["express", "body-parser"]}, "9": "{\"initiate_commands\": [[\"npm\", \"install\"], [\"node\", \"server.js\"]], \"requirements\": [express, ejs, nodemon]}", "14": "{\"initiate_commands\": [[\"npm\", \"install\"], [\"node\", \"app.js\"]], \"requirements\": [\"express\", \"path\"]} \n\nHomepage's URL: http://localhost:3000 \n\nNote: The homepage will display a blue-colored heading with the text \"Hello World!\" in an HTML page.", "15": {"initiate_commands": [["node", "index.js"]], "requirements": ["express", "path"]}, "20": {"initiate_commands": [["npm", "install"], ["node", "server.js"]], "requirements": ["express", "http-server"]}}