{"1": [{"page": "HomePage", "function": [{"function": "View Introduction", "parameter": [{"name": "test_url", "answer": "http://localhost:8000/"}, {"name": "introduction_element_id", "answer": "home-header"}]}, {"function": "Navigation to Calculator", "parameter": [{"name": "test_url", "answer": "http://localhost:8000/"}, {"name": "navigate_button_id", "answer": "bmi-link"}, {"name": "calculator_element_id", "answer": "bmi-header"}]}]}, {"page": "BMICalculatorPage", "function": [{"function": "Input Height", "parameter": [{"name": "test_url", "answer": "http://localhost:8000/bmi-calculator/"}, {"name": "height_input_box_id", "answer": "id_height"}]}, {"function": "Input Weight", "parameter": [{"name": "test_url", "answer": "http://localhost:8000/bmi-calculator/"}, {"name": "weight_input_box_id", "answer": "id_weight"}]}, {"function": "Submit Data", "parameter": [{"name": "test_url", "answer": "http://localhost:8000/bmi-calculator/"}, {"name": "height_input_box_id", "answer": "id_height"}, {"name": "weight_input_box_id", "answer": "id_weight"}, {"name": "submit_button_id", "answer": "calculate-button"}]}, {"function": "Display BMI Result", "parameter": [{"name": "test_url", "answer": "http://localhost:8000/bmi-calculator/"}, {"name": "bmi_result_id", "answer": "bmi-result"}]}, {"function": "Display BMI Category", "parameter": [{"name": "test_url", "answer": "http://localhost:8000/bmi-calculator/"}, {"name": "bmi_category_id", "answer": "bmi-category"}]}, {"function": "Provide Interpretation", "parameter": [{"name": "test_url", "answer": "http://localhost:8000/bmi-calculator/"}, {"name": "interpretation_id", "answer": "advice-list"}]}, {"function": "Reset Form", "parameter": [{"name": "test_url", "answer": "http://localhost:8000/bmi-calculator/"}, {"name": "height_input_box_id", "answer": "id_height"}, {"name": "weight_input_box_id", "answer": "id_weight"}, {"name": "reset_button_id", "answer": "reset-button"}]}, {"function": "Link to Health Advice", "parameter": [{"name": "test_url", "answer": "http://localhost:8000/bmi-calculator/"}, {"name": "health_advice_id", "answer": "advice-header"}]}]}], "2": [{"page": "Home Page", "function": [{"function": "Select Source Currency", "parameter": [{"name": "test_url", "answer": "http://localhost:8000/"}, {"name": "source_currency_dropdown_id", "answer": "id_source_currency"}, {"name": "source_currency_value", "answer": "USD"}]}, {"function": "Select Target Currency", "parameter": [{"name": "test_url", "answer": "http://localhost:8000/"}, {"name": "target_currency_dropdown_id", "answer": "id_target_currency"}, {"name": "target_currency_value", "answer": "EUR"}]}, {"function": "Enter Amount", "parameter": [{"name": "test_url", "answer": "http://localhost:8000/"}, {"name": "amount_input_box_id", "answer": "id_amount"}, {"name": "amount_value", "answer": "100.00"}]}, {"function": "Convert Button", "parameter": [{"name": "convert_button_id", "answer": "id_convert_button"}]}, {"function": "Display Conversion Result", "parameter": [{"name": "test_url", "answer": "http://localhost:8000/"}, {"name": "result_box_id", "answer": "id_result"}]}, {"function": "Exchange Rate Info", "parameter": [{"name": "test_url", "answer": "http://localhost:8000/"}, {"name": "exchange_rate_info_id", "answer": "id_exchange_rate_info"}]}]}, {"page": "Currency Details Page", "function": [{"function": "Currency Information", "parameter": [{"name": "test_url", "answer": "http://localhost:8000/trends/"}, {"name": "currency_info_id", "answer": "id_currency_info"}]}, {"function": "Historical Exchange Rates", "parameter": [{"name": "test_url", "answer": "http://localhost:8000/trends/"}, {"name": "historical_rates_id", "answer": "id_historical_rates"}]}]}], "3": [{"page": "Home", "function": [{"function": "Display Welcome Message", "parameter": [{"name": "test_url", "answer": "http://localhost:8000/"}, {"name": "swelcome_message_id", "answer": "home-title"}]}, {"function": "Navigation Button", "parameter": [{"name": "test_url", "answer": "http://localhost:8000/"}, {"name": "navigation_button_id", "answer": "None"}, {"name": "generator_id", "answer": "password-form"}]}]}, {"page": "PasswordOptions", "function": [{"function": "Length Input", "parameter": [{"name": "test_url", "answer": "http://localhost:8000/generator/"}, {"name": "length_input_id", "answer": "length"}]}, {"function": "Include Uppercase", "parameter": [{"name": "include_uppercase_id", "answer": "include_uppercase"}]}, {"function": "Include Lowercase", "parameter": [{"name": "include_lowercase_id", "answer": "include_lowercase"}]}, {"function": "Include Numbers", "parameter": [{"name": "include_numbers_id", "answer": "include_numbers"}]}, {"function": "Include Symbols", "parameter": [{"name": "include_symbols_id", "answer": "include_symbols"}]}, {"function": "Generate Button", "parameter": [{"name": "generate_button_id", "answer": "None"}]}]}, {"page": "GeneratedPassword", "function": [{"function": "Display Password", "parameter": [{"name": "display_password_id", "answer": "password"}]}, {"function": "Rule Check 1", "parameter": [{"name": "display_password_id", "answer": "password"}]}, {"function": "Copy to Clipboard", "parameter": [{"name": "display_password_id", "answer": "password"}, {"name": "copy_button_id", "answer": "copy-button"}]}, {"function": "Generate Another Password", "parameter": [{"name": "test_url", "answer": "http://localhost:8000/generator/"}, {"name": "length_input_id", "answer": "length"}, {"name": "include_lowercase_id", "answer": "include_lowercase"}, {"name": "include_numbers_id", "answer": "include_numbers"}, {"name": "generate_button_id", "answer": "None"}, {"name": "display_password_id", "answer": "password"}]}, {"function": "Rule Check 2", "parameter": [{"name": "display_password_id", "answer": "password"}]}]}, {"page": "About", "function": [{"function": "About Link", "parameter": [{"name": "test_url", "answer": "http://localhost:8000/"}, {"name": "about_link_id", "answer": "None"}]}, {"function": "Description", "parameter": [{"name": "description_id", "answer": "about-us-content"}]}]}], "5": [{"page": "Home", "function": [{"function": "Welcome Message", "parameter": [{"name": "test_url", "answer": "http://localhost:8000/"}]}, {"function": "Introduction to Converter", "parameter": [{"name": "test_url", "answer": "http://localhost:8000/"}, {"name": "introduction_id", "answer": "home-paragraph"}]}, {"function": "Navigation Links", "parameter": [{"name": "test_url", "answer": "http://localhost:8000/"}, {"name": "convert_link_id", "answer": "convert-link"}, {"name": "expected_url", "answer": "http://localhost:8000/convert/"}]}]}, {"page": "Convert", "function": [{"function": "Markdown Input Area", "parameter": [{"name": "test_url", "answer": "http://localhost:8000/convert/"}, {"name": "markdown_input_id", "answer": "file-input"}]}, {"function": "Convert Button", "parameter": [{"name": "convert_button_id", "answer": "submit-button"}]}, {"function": "HTML Output Area", "parameter": [{"name": "html_output_id", "answer": "html-output"}]}, {"function": "Rule Check 1", "parameter": [{"name": "html_output_id", "answer": "html-output"}]}, {"function": "Upload File", "parameter": [{"name": "test_url", "answer": "http://localhost:8000/convert/"}, {"name": "upload_file_id", "answer": "file-input"}, {"name": "upload_file_btn_id", "answer": "submit-button"}]}, {"function": "Download HTML", "parameter": [{"name": "download_html_btn_id", "answer": "None"}, {"name": "default_download_path", "answer": "/Users/username/Downloads/"}]}, {"function": "Rule Check 2", "parameter": [{"name": "default_download_path", "answer": "/Users/username/Downloads/"}]}]}, {"page": "About", "function": [{"function": "Team Information", "parameter": [{"name": "test_url", "answer": "http://localhost:8000/about/"}]}, {"function": "FAQ Section", "parameter": [{"name": "test_url", "answer": "http://localhost:8000/about/"}]}]}], "6": [{"page": "Home", "function": [{"function": "View Dashboard", "parameter": [{"name": "test_url", "answer": "http://localhost:8000/"}, {"name": "navigate_dashboard_id", "answer": "home-title"}]}, {"function": "Navigate to Todo Lists", "parameter": [{"name": "test_url", "answer": "http://localhost:8000/"}, {"name": "navigate_todo_lists_id", "answer": "todo-list-link"}]}]}, {"page": "Todo List", "function": [{"function": "Create New List", "parameter": [{"name": "test_url", "answer": "http://localhost:8000/todos/"}, {"name": "list_input_box_id", "answer": "id_title"}, {"name": "create_button_id", "answer": "create-todo-list-btn"}]}, {"function": "View Tasks", "parameter": [{"name": "test_url", "answer": "http://localhost:8000/todos/"}, {"name": "todo_list_selector_class_name", "answer": "list-group-item"}]}]}, {"page": "Task", "function": [{"function": "Add New Task", "parameter": [{"name": "task_input_box_id", "answer": "id_title"}, {"name": "add_button_id", "answer": "create-task-btn"}]}, {"function": "Edit Task", "parameter": [{"name": "task_selector_class", "answer": "list-group-item"}, {"name": "edit_input_box_id", "answer": "id_title"}, {"name": "save_button_id", "answer": "edit-todo-item-btn"}]}, {"function": "Mark Task as Completed", "parameter": [{"name": "complete_button_class", "answer": "complete-task-link"}]}, {"function": "Delete Task", "parameter": [{"name": "task_selector_class", "answer": "list-group-item"}, {"name": "delete_button_id", "answer": "delete-task-link"}]}, {"function": "Add New Task 2", "parameter": [{"name": "task_input_box_id", "answer": "id_title"}, {"name": "add_button_id", "answer": "create-task-btn"}]}, {"function": "Add New Task 3", "parameter": [{"name": "task_input_box_id", "answer": "id_title"}, {"name": "add_button_id", "answer": "create-task-btn"}]}, {"function": "View Task 2", "parameter": [{"name": "test_url", "answer": "http://localhost:8000/todos/view_task/1/"}, {"name": "task_class", "answer": "list-group-item"}]}, {"function": "Mark Task as Completed 2", "parameter": [{"name": "complete_button_class", "answer": "complete-task-link"}]}]}, {"page": "Analysis", "function": [{"function": "Return to Todolists", "parameter": [{"name": "return_link_id", "answer": "todo-list-link"}]}, {"function": "Return to Homepage", "parameter": [{"name": "return_link_id", "answer": "home-title"}]}, {"function": "View Task Completion Chart", "parameter": [{"name": "test_url", "answer": "http://localhost:8000/analysis/"}, {"name": "chart_id", "answer": "myChart"}]}, {"function": "View Task Distribution Chart", "parameter": [{"name": "test_url", "answer": "http://localhost:8000/analysis/"}, {"name": "chart_id", "answer": "myChart"}]}, {"function": "Return to Homepage 2", "parameter": [{"name": "return_link_id", "answer": "home-title"}]}]}, {"page": "Todo List 2", "function": [{"function": "Edit List", "parameter": [{"name": "test_url", "answer": "http://localhost:8000/todos/edit/1/"}, {"name": "edit_button_xpath", "answer": "//a[@href='/todos/edit/1/']"}, {"name": "list_input_box_id", "answer": "id_title"}, {"name": "save_button_id", "answer": "edit-todo-btn"}]}, {"function": "Delete List", "parameter": [{"name": "test_url", "answer": "http://localhost:8000/todos/delete/1/"}, {"name": "delete_button_xpath", "answer": "//a[@href='/todos/delete/1/']"}]}]}], "8": [{"page": "Home", "function": [{"function": "View Current Date", "parameter": [{"name": "test_url", "answer": "http://localhost:8000/"}, {"name": "current_date_id", "answer": "current-date"}]}, {"function": "Quick Access to Calendar", "parameter": [{"name": "test_url", "answer": "http://localhost:8000/"}, {"name": "calendar_id", "answer": "calendar-link"}]}]}, {"page": "Calendar", "function": [{"function": "View Calendar", "parameter": []}, {"function": "Add Event", "parameter": [{"name": "event_input_id", "answer": "event-title-input"}, {"name": "add_event_id", "answer": "add-event-link"}, {"name": "description_input_id", "answer": "event-description-input"}, {"name": "datetime_id", "answer": "event-datetime-input"}, {"name": "save_event_id", "answer": "save-event-button"}]}, {"function": "Switch Month", "parameter": [{"name": "year_id", "answer": "year-selector"}, {"name": "month_id", "answer": "month-selector"}, {"name": "switch_button_id", "answer": "switch-month-button"}]}, {"function": "Add Event Page Back Home", "parameter": [{"name": "test_url", "answer": "http://localhost:8000/add-event/"}, {"name": "back_button_id", "answer": "back-to-home-button"}]}]}, {"page": "Event Details", "function": [{"function": "List All Events", "parameter": [{"name": "list_link_id", "answer": "list-events-link"}]}, {"function": "Edit Event", "parameter": [{"name": "edit_button_class_name", "answer": "edit-event-button"}, {"name": "event_input_id", "answer": "event-title-input"}, {"name": "description_input_id", "answer": "event-description-input"}, {"name": "datetime_id", "answer": "event-datetime-input"}, {"name": "save_event_id", "answer": "save-event-button"}]}, {"function": "Delete Event", "parameter": [{"name": "delete_button_class_name", "answer": "delete-event-button"}, {"name": "test_url", "answer": "http://localhost:8000/list-events/"}]}, {"function": "Search Events", "parameter": [{"name": "search_input_id", "answer": "search-input-box"}, {"name": "search_button_id", "answer": "search-button"}]}, {"function": "View Event Details 1", "parameter": [{"name": "event_detail_button_class_name", "answer": "view-event-details-button"}, {"name": "test_url", "answer": "http://localhost:8000/list-events/"}]}, {"function": "View Event Details 2", "parameter": [{"name": "test_url", "answer": "http://localhost:8000/"}, {"name": "event_detail_button_class_name", "answer": "view-event-details-button"}]}, {"function": "Event Detail Page Back", "parameter": [{"name": "test_url", "answer": "http://localhost:8000/event-details/"}, {"name": "back_button_id", "answer": "back-to-home-button"}]}]}, {"page": "Help", "function": [{"function": "FAQ", "parameter": [{"name": "test_url", "answer": "http://localhost:8000/"}, {"name": "faq_link_id", "answer": "faq-link"}, {"name": "faq_id", "answer": "faqs"}]}, {"function": "FAQs Back Home", "parameter": [{"name": "back_button_id", "answer": "back-to-home-button"}]}, {"function": "User Guide", "parameter": [{"name": "test_url", "answer": "http://localhost:8000/"}, {"name": "user_guide_link_id", "answer": "user-guide-link"}, {"name": "user_guide_id", "answer": "user-guide"}]}, {"function": "User Guide Back Home Test", "parameter": [{"name": "back_button_id", "answer": "back-to-home-button"}]}]}], "11": [{"page": "Home", "function": [{"function": "Display Welcome Message", "parameter": [{"name": "test_url", "answer": "http://localhost:8000/"}, {"name": "title_text", "answer": "Project Review Site"}]}, {"function": "Navigation Link", "parameter": [{"name": "test_url", "answer": "http://localhost:8000/"}, {"name": "home_link_id", "answer": "home-link"}, {"name": "about_link_id", "answer": "about-link"}, {"name": "about_expected_url", "answer": "http://localhost:8000/about/"}, {"name": "home_expected_url", "answer": "http://localhost:8000/"}]}, {"function": "Upload File1", "parameter": [{"name": "test_url", "answer": "http://localhost:8000/"}, {"name": "json_file_id", "answer": "id_json_file"}, {"name": "upload_file_btn_id", "answer": "upload-button"}]}, {"function": "Upload File2", "parameter": [{"name": "test_url", "answer": "http://localhost:8000/"}, {"name": "json_file_id", "answer": "id_json_file"}, {"name": "upload_file_btn_id", "answer": "upload-button"}]}, {"function": "Test Code Review1", "parameter": [{"name": "test_url", "answer": "http://localhost:8000/"}, {"name": "project_class_name", "answer": "project-item"}, {"name": "notes_class_name", "answer": "review-textarea"}, {"name": "select_class_name", "answer": "rating-select"}, {"name": "status_class_name", "answer": "status-display"}, {"name": "submit_button", "answer": "submit-review-button"}, {"name": "success_text", "answer": "Review submitted successfully."}]}, {"function": "Test Code Review2", "parameter": [{"name": "test_url", "answer": "http://localhost:8000/"}, {"name": "project_class_name", "answer": "project-item"}, {"name": "notes_class_name", "answer": "review-textarea"}, {"name": "select_class_name", "answer": "rating-select"}, {"name": "status_class_name", "answer": "status-display"}, {"name": "submit_button", "answer": "submit-review-button"}, {"name": "select_status_text", "answer": "Select a rating"}]}]}, {"page": "About", "function": [{"function": "Test Description", "parameter": [{"name": "test_url", "answer": "http://localhost:8000/about/"}, {"name": "expected_description", "answer": "This is a project review site."}]}]}], "12": [{"page": "Home", "function": [{"function": "View Home", "parameter": [{"name": "test_url", "answer": "http://localhost:8000/"}, {"name": "title_text", "answer": "Welcome to Accounting and Cashier Management"}, {"name": "signup_id", "answer": "signup-link"}, {"name": "signup_url", "answer": "http://localhost:8000/signup/"}, {"name": "login_id", "answer": "login-link"}, {"name": "login_url", "answer": "http://localhost:8000/login/"}]}, {"function": "View Dashboard", "parameter": [{"name": "test_url", "answer": "http://localhost:8000/"}, {"name": "title_text", "answer": "Accounting and Cashier Management"}]}, {"function": "Sign Up", "parameter": [{"name": "test_url", "answer": "http://localhost:8000/"}, {"name": "signup_id", "answer": "signup-link"}, {"name": "id_username_field", "answer": "username"}, {"name": "id_email_field", "answer": "email"}, {"name": "id_password1_field", "answer": "password1"}, {"name": "id_password2_field", "answer": "password2"}, {"name": "sign_up_button", "answer": "submit-button"}]}, {"function": "Log In", "parameter": [{"name": "test_url", "answer": "http://localhost:8000/"}, {"name": "login_id", "answer": "login-link"}, {"name": "username_field", "answer": "username-input"}, {"name": "password_field", "answer": "password-input"}, {"name": "login_button", "answer": "submit-button"}]}]}, {"page": "Frontend (Employee Portal)", "function": [{"function": "Submit Claim", "parameter": [{"name": "test_url", "answer": "http://localhost:8000/submit_claim/"}, {"name": "category_field", "answer": "id_category"}, {"name": "amount_field", "answer": "id_amount"}, {"name": "description_field", "answer": "id_description"}, {"name": "submit_claim_button", "answer": "submit-button"}]}, {"function": "Submit Claim2", "parameter": [{"name": "test_url", "answer": "http://localhost:8000/submit_claim/"}, {"name": "category_field", "answer": "id_category"}, {"name": "amount_field", "answer": "id_amount"}, {"name": "description_field", "answer": "id_description"}, {"name": "submit_claim_button", "answer": "submit-button"}]}, {"function": "Submit Claim3", "parameter": [{"name": "test_url", "answer": "http://localhost:8000/submit_claim/"}, {"name": "category_field", "answer": "id_category"}, {"name": "amount_field", "answer": "id_amount"}, {"name": "description_field", "answer": "id_description"}, {"name": "submit_claim_button", "answer": "submit-button"}]}, {"function": "View Claim Status", "parameter": [{"name": "test_url", "answer": "http://localhost:8000/claim_status/"}, {"name": "status_text", "answer": "Pending"}]}, {"function": "Edit Submitted Claim", "parameter": [{"name": "test_url", "answer": "http://localhost:8000/edit_claim/"}, {"name": "edit_class_name", "answer": "edit-link"}, {"name": "category_field", "answer": "id_category"}, {"name": "amount_field", "answer": "id_amount"}, {"name": "description_field", "answer": "id_description"}, {"name": "save_changes_button", "answer": "submit-button"}]}]}, {"page": "Admin Page (Accounting Administrator Portal)", "function": [{"function": "Approve Claim", "parameter": [{"name": "admin_url", "answer": "http://localhost:8000/admin/"}, {"name": "username_id", "answer": "id_username"}, {"name": "password_id", "answer": "id_password"}, {"name": "login_button_xpath", "answer": "//input[@type='submit']"}, {"name": "claims_xpath", "answer": "//a[text()='Claims']"}, {"name": "edit_button_class_name", "answer": "edit-link"}, {"name": "status_id", "answer": "id_status"}, {"name": "save_button_xpath", "answer": "//input[@type='submit']"}, {"name": "logout_button_xpath", "answer": "//a[text()='Logout']"}, {"name": "test_url", "answer": "http://localhost:8000/"}, {"name": "login_id", "answer": "login-link"}, {"name": "username_field", "answer": "username-input"}, {"name": "password_field", "answer": "password-input"}, {"name": "login_button", "answer": "submit-button"}, {"name": "claim_status_url", "answer": "http://localhost:8000/claim_status/"}, {"name": "status_class_name", "answer": "status"}]}, {"function": "Reject Claim with Reason", "parameter": [{"name": "admin_url", "answer": "http://localhost:8000/admin/"}, {"name": "username_id", "answer": "id_username"}, {"name": "password_id", "answer": "id_password"}, {"name": "login_button_xpath", "answer": "//input[@type='submit']"}, {"name": "claims_xpath", "answer": "//a[text()='Claims']"}, {"name": "edit_button_class_name", "answer": "edit-link"}, {"name": "status_id", "answer": "id_status"}, {"name": "rejection_reason_id", "answer": "id_rejection_reason"}, {"name": "save_button_xpath", "answer": "//input[@type='submit']"}, {"name": "logout_button_xpath", "answer": "//a[text()='Logout']"}, {"name": "test_url", "answer": "http://localhost:8000/"}, {"name": "login_id", "answer": "login-link"}, {"name": "username_field", "answer": "username-input"}, {"name": "password_field", "answer": "password-input"}, {"name": "login_button", "answer": "submit-button"}, {"name": "claim_status_url", "answer": "http://localhost:8000/claim_status/"}, {"name": "status_class_name", "answer": "status"}]}, {"function": "View Claim Details", "parameter": [{"name": "admin_url", "answer": "http://localhost:8000/admin/"}, {"name": "username_id", "answer": "id_username"}, {"name": "password_id", "answer": "id_password"}, {"name": "login_button_xpath", "answer": "//input[@type='submit']"}, {"name": "claims_xpath", "answer": "//a[text()='Claims']"}, {"name": "edit_button_class_name", "answer": "edit-link"}]}, {"function": "Search and Filter Claims", "parameter": [{"name": "admin_url", "answer": "http://localhost:8000/admin/"}, {"name": "claims_xpath", "answer": "//a[text()='Claims']"}, {"name": "search_id", "answer": "id_search"}, {"name": "search_button_xpath", "answer": "//input[@type='submit']"}]}]}, {"page": "Budget Control Application", "function": [{"function": "Add Budget", "parameter": [{"name": "budget_url", "answer": "http://localhost:8000/analysis/"}, {"name": "add_button_xpath", "answer": "//button[text()='Add']"}, {"name": "category_id", "answer": "id_category"}, {"name": "limit_id", "answer": "id_limit"}, {"name": "save_button_xpath", "answer": "//input[@type='submit']"}]}, {"function": "Analyze Expense Balances", "parameter": [{"name": "budget_url", "answer": "http://localhost:8000/analysis/"}, {"name": "balance_class_name", "answer": "balance"}]}, {"function": "Generate Reports", "parameter": [{"name": "budget_url", "answer": "http://localhost:8000/analysis/"}]}, {"function": "Send Budget Alerts", "parameter": [{"name": "budget_url", "answer": "http://localhost:8000/analysis/"}, {"name": "over_balanace_class_name", "answer": "warning"}]}]}], "14": [{"page": "HelloWorld", "function": [{"function": "DisplayText", "parameter": [{"name": "test_url", "answer": "http://localhost:8000/"}]}, {"function": "BasicStyling", "parameter": [{"name": "test_url", "answer": "http://localhost:8000/"}]}, {"function": "PageTitle", "parameter": [{"name": "test_url", "answer": "http://localhost:8000/"}]}, {"function": "MetaTags", "parameter": [{"name": "test_url", "answer": "http://localhost:8000/"}]}]}], "15": [{"page": "Home", "function": [{"function": "Button to 'HelloWorld' page", "parameter": [{"name": "test_url", "answer": "http://localhost:8000/helloworld/"}]}]}, {"page": "HelloWorld", "function": [{"function": "Display 'HelloWorld' message", "parameter": []}]}], "17": [{"page": "Data Preparation", "function": [{"function": "CheckFileExistence", "parameter": [{"name": "entry", "answer": "17-stdanswer.py"}, {"name": "error_message", "answer": "The file 17-stdanswer.py does not exist."}]}, {"function": "ValidateNullValue", "parameter": [{"name": "entry", "answer": "Gamedata.xlsx"}, {"name": "error_message", "answer": "There are missing values in the Gamedata.xlsx file."}]}, {"function": "ValidateEmptyFile", "parameter": [{"name": "entry", "answer": "Gamedata.xlsx"}, {"name": "error_message", "answer": "The Gamedata.xlsx file is empty."}]}]}, {"page": "Model Creation and Output", "function": [{"function": "RunProject", "parameter": [{"name": "entry", "answer": "17-stdanswer.py"}]}, {"function": "OutputFileCheck", "parameter": []}]}], "18": [{"page": "Main Menu", "function": [{"function": "Welcome Message", "parameter": [{"name": "expected_output", "answer": "Main Menu:\n1. Start Game\n2. Help\n3. Quit"}]}, {"function": "Help in Main Menu", "parameter": [{"name": "help_in_main_menu_command", "answer": "2"}, {"name": "expected_output", "answer": "Type '1' to start a new game, '2' for help, or '3' to quit."}]}, {"function": "Wrong Selection Check", "parameter": [{"name": "expected_output", "answer": "Invalid choice. Please choose a valid option."}]}, {"function": "Start Game", "parameter": [{"name": "start_game_command", "answer": "1"}, {"name": "expected_output", "answer": "Directory: /\nContents:\nhome\nforest\ncave"}]}]}, {"page": "Game", "function": [{"function": "Display Help", "parameter": [{"name": "help_in_game", "answer": "help"}, {"name": "expected_output", "answer": "Available commands:\n- ls: list directory contents\n- cd <directory>: change directory\n- inventory: view your current inventory\n- help: display this help message\n- quit: exit the game"}]}, {"function": "Look Around", "parameter": [{"name": "expected_output", "answer": "Directory: /\nContents:\nhome\nforest\ncave"}]}, {"function": "Move Player", "parameter": [{"name": "direction", "answer": "home"}, {"name": "expected_output", "answer": "Changed directory to: /home"}]}, {"function": "Move Back", "parameter": [{"name": "expected_output", "answer": "Invalid directory. Please try again."}]}, {"function": "Check Inventory 1", "parameter": [{"name": "check_inventory_command", "answer": "inventory"}, {"name": "expected_output", "answer": "Your inventory is empty."}]}, {"function": "Pick Item", "parameter": [{"name": "directions", "answer": "cave,treasure_room"}, {"name": "expected_output", "answer": "Changed directory to: /cave/treasure_room"}]}, {"function": "Check Inventory 2", "parameter": [{"name": "check_inventory_command", "answer": "inventory"}, {"name": "expected_output", "answer": "Your current inventory: golden_key"}]}, {"function": "Win the Game", "parameter": [{"name": "directions", "answer": "..,..,forest"}, {"name": "expected_output", "answer": "Changed directory to: /forest"}]}]}, {"page": "Main Menu 2", "function": [{"function": "Exit Game", "parameter": [{"name": "exit_command", "answer": "3"}, {"name": "expected_output", "answer": ""}]}]}]}