{"1": [{"file": "start.py", "path": "start.py", "code": "import subprocess\n\nsubprocess.run(\"npm install express\", shell=True)\nsubprocess.run(\"node server.js\", shell=True)"}, {"file": "server.js", "path": "server.js", "code": "const express = require('express');\nconst path = require('path');\nconst app = express();\nconst PORT = 3000;\n\napp.use(express.static(path.join(__dirname, 'public')));\n\napp.get('/', (req, res) => {\n  res.sendFile(path.join(__dirname, 'public', 'index.html'));\n});\n\napp.listen(PORT, () => {\n  console.log(`Server running on http://localhost:${PORT}`);\n});"}, {"file": "package.json", "path": "package.json", "code": "{\n  \"name\": \"bmi-calculator\",\n  \"version\": \"1.0.0\",\n  \"description\": \"\",\n  \"main\": \"server.js\",\n  \"scripts\": {\n    \"start\": \"node server.js\"\n  },\n  \"keywords\": [],\n  \"author\": \"\",\n  \"license\": \"ISC\",\n  \"dependencies\": {\n    \"express\": \"^4.18.2\"\n  }\n}"}, {"file": "index.html", "path": "public/index.html", "code": "<!DOCTYPE html>\n<html>\n<head>\n  <title>BMI Calculator</title>\n  <style>\n    .container { text-align: center; margin-top: 50px; }\n    input, button { padding: 10px; margin: 10px; }\n    #result { margin-top: 20px; font-size: 1.2em; }\n  </style>\n</head>\n<body>\n  <div class=\"container\">\n    <h1>BMI Calculator</h1>\n    <label for=\"weight\">Weight (kg):</label>\n    <input type=\"number\" id=\"weight\" class=\"input-field\">\n    <label for=\"height\">Height (cm):</label>\n    <input type=\"number\" id=\"height\" class=\"input-field\">\n    <button onclick=\"calculateBMI()\">Calculate BMI</button>\n    <div id=\"result\" class=\"result\"></div>\n  </div>\n  <script>\n    function calculateBMI() {\n      const weight = parseFloat(document.getElementById('weight').value);\n      const height = parseFloat(document.getElementById('height').value);\n      if (isNaN(weight) || isNaN(height) || height === 0) {\n        document.getElementById('result').innerText = 'Please enter valid numbers.';\n        return;\n      }\n      const bmi = (weight / ((height / 100) ** 2)).toFixed(2);\n      document.getElementById('result').innerText = `Your BMI is ${bmi}.`;\n    }\n  </script>\n</body>\n</html>"}], "8": [{"file": "app.js", "path": "./app.js", "code": "const express = require('express');\nconst path = require('path');\nconst { format, getDaysInMonth, startOfMonth, eachDayOfInterval, isToday } = require('date-fns');\n\nconst app = express();\nconst PORT = 3000;\n\napp.set('view engine', 'ejs');\napp.use(express.static(path.join(__dirname, 'public')));\n\napp.get('/', (req, res) => {\n  const today = new Date();\n  const firstDayOfMonth = startOfMonth(today);\n  const daysInMonth = getDaysInMonth(today);\n  const days = eachDayOfInterval({\n    start: firstDayOfMonth,\n    end: new Date(today.getFullYear(), today.getMonth() + 1, 0)\n  });\n\n  res.render('index', {\n    days,\n    today\n  });\n});\n\napp.listen(PORT, () => {\n  console.log(`Server running at http://localhost:${PORT}`);\n});"}, {"file": "views/index.ejs", "path": "./views/index.ejs", "code": "<!DOCTYPE html>\n<html>\n<head>\n  <title>Monthly Calendar</title>\n  <link rel=\"stylesheet\" href=\"/styles.css\">\n</head>\n<body>\n  <h1 id=\"calendar-title\">Monthly Calendar</h1>\n  <table id=\"calendar\" class=\"calendar-table\">\n    <thead>\n      <tr>\n        <th>Sun</th>\n        <th>Mon</th>\n        <th>Tue</th>\n        <th>Wed</th>\n        <th>Thu</th>\n        <th>Fri</th>\n        <th>Sat</th>\n      </tr>\n    </thead>\n    <tbody>\n      <% let week = [];\n         let currentDay = 0;\n         const daysInMonth = days.length;\n         const today = new Date();\n         const currentMonth = today.getMonth();\n         const currentYear = today.getFullYear();\n      %>\n      <% for (let i = 0; i < days.length; i++) {\n          const day = days[i];\n          const dayOfMonth = day.getDate();\n          const dayOfWeek = day.getDay();\n          const isCurrentDay = isToday(day);\n          \n          week.push(`<td class=\"day ${isCurrentDay ? 'today' : ''}\" data-date=\"${format(day, 'yyyy-MM-dd')}\">${dayOfMonth}</td>`);\n          \n          if (dayOfWeek === 6) {\n            // Saturday, end of week\n            week.push(`</tr>`);\n            week.push(`<tr>`);\n            week = [];\n          }\n        } %>\n      <% if (week.length > 0) {\n          week.push(`</tr>`);\n        } %>\n      <%= week.join('') %>\n    </tbody>\n  </table>\n</body>\n</html>"}, {"file": "public/styles.css", "path": "./public/styles.css", "code": "body {\n  font-family: Arial, sans-serif;\n  padding: 20px;\n}\n\n#calendar-title {\n  text-align: center;\n  margin-bottom: 20px;\n}\n\n.calendar-table {\n  width: 100%;\n  border-collapse: collapse;\n  margin-top: 20px;\n}\n\n.calendar-table th, .calendar-table td {\n  border: 1px solid #ccc;\n  padding: 10px;\n  text-align: center;\n}\n\n.day {\n  cursor: pointer;\n}\n\n.day.today {\n  background-color: #a8e6a0;\n  font-weight: bold;\n}"}, {"file": "start.py", "path": "./start.py", "code": "import subprocess\n\nsubprocess.run([\"npm\", \"install\", \"express\", \"ejs\", \"date-fns\"], shell=True)\nsubprocess.run([\"node\", \"app.js\"], shell=True)"}, {"file": "package.json", "path": "./package.json", "code": "{\n  \"name\": \"monthly-calendar\",\n  \"version\": \"1.0.0\",\n  \"description\": \"Monthly calendar web application\",\n  \"main\": \"app.js\",\n  \"scripts\": {\n    \"start\": \"node app.js\"\n  },\n  \"dependencies\": {\n    \"express\": \"^4.18.2\",\n    \"ejs\": \"^3.1.9\",\n    \"date-fns\": \"^2.30.0\"\n  }\n}"}], "9": [{"file": "app.js", "path": "app.js", "code": "const express = require('express');\nconst path = require('path');\n\nconst app = express();\nconst PORT = 3000;\n\n// Serve static files from the 'public' directory\napp.use(express.static(path.join(__dirname, 'public')));\n\napp.get('/', (req, res) => {\n  res.sendFile(path.join(__dirname, 'public', 'index.html'));\n});\n\napp.listen(PORT, () => {\n  console.log(`Server running at http://localhost:${PORT}`);\n});"}, {"file": "public/index.html", "path": "public/index.html", "code": "<!DOCTYPE html>\n<html lang=\"en\">\n<head>\n  <meta charset=\"UTF-8\">\n  <meta name=\"viewport\" content=\"width=device-width, initial-scale=1.0\">\n  <title>AI Chatbot Introduction</title>\n  <link rel=\"stylesheet\" href=\"styles.css\">\n</head>\n<body>\n  <header id=\"header\" class=\"container\">\n    <h1>Welcome to the Future of AI Chatbots</h1>\n  </header>\n  \n  <section id=\"features\" class=\"container\">\n    <h2>Key Features</h2>\n    <ul class=\"feature-list\">\n      <li class=\"feature-item\">Natural Language Understanding</li>\n      <li class=\"feature-item\">24/7 Availability</li>\n      <li class=\"feature-item\">Multi-Language Support</li>\n    </ul>\n  </section>\n\n  <section id=\"contact\" class=\"container\">\n    <h2>Contact Us</h2>\n    <form id=\"contact-form\" class=\"contact-form\">\n      <input type=\"text\" id=\"name\" class=\"form-input\" placeholder=\"Your Name\">\n      <input type=\"email\" id=\"email\" class=\"form-input\" placeholder=\"Your Email\">\n      <textarea id=\"message\" class=\"form-input\" placeholder=\"Your Message\"></textarea>\n      <button type=\"submit\" class=\"submit-btn\">Send</button>\n    </form>\n  </section>\n\n  <script src=\"script.js\"></script>\n</body>\n</html>"}, {"file": "public/styles.css", "path": "public/styles.css", "code": "body {\n  font-family: Arial, sans-serif;\n  margin: 0;\n  padding: 0;\n  background-color: #f4f4f4;\n}\n\n.container {\n  padding: 20px;\n  max-width: 800px;\n  margin: auto;\n}\n\n#header {\n  background-color: #007BFF;\n  color: white;\n  text-align: center;\n  padding: 40px 20px;\n}\n\n#features {\n  background-color: #e9ecef;\n  padding: 30px 20px;\n}\n\n.feature-list {\n  list-style-type: none;\n  padding: 0;\n}\n\n.feature-item {\n  background: white;\n  margin: 10px 0;\n  padding: 15px;\n  border-left: 5px solid #007BFF;\n}\n\n#contact {\n  background-color: #ffffff;\n  padding: 30px 20px;\n  margin-top: 20px;\n}\n\n.contact-form {\n  display: flex;\n  flex-direction: column;\n}\n\n.form-input {\n  padding: 10px;\n  margin-bottom: 15px;\n  border: 1px solid #ccc;\n  border-radius: 4px;\n}\n\n.submit-btn {\n  padding: 10px;\n  background-color: #007BFF;\n  color: white;\n  border: none;\n  border-radius: 4px;\n  cursor: pointer;\n}\n\n.submit-btn:hover {\n  background-color: #0056b3;\n}"}, {"file": "public/script.js", "path": "public/script.js", "code": "document.getElementById('contact-form').addEventListener('submit', function(e) {\n  e.preventDefault();\n  alert('Thank you for your message!');\n});"}, {"file": "package.json", "path": "package.json", "code": "{\n  \"name\": \"ai-chatbot-intro\",\n  \"version\": \"1.0.0\",\n  \"description\": \"AI Chatbot Product Introduction Website\",\n  \"main\": \"app.js\",\n  \"scripts\": {\n    \"start\": \"node app.js\"\n  },\n  \"dependencies\": {\n    \"express\": \"^4.18.2\"\n  }\n}"}, {"file": "start.py", "path": "start.py", "code": "import subprocess\n\n# Install dependencies\nsubprocess.run(['npm', 'install', 'express'], shell=True)\n\n# Start the server\nsubprocess.run(['npm', 'start'], shell=True)"}], "11": [{"file": "app.js", "path": "app.js", "code": "const express = require('express');\nconst mongoose = require('mongoose');\nconst testRoutes = require('./routes/testRoutes');\n\nconst app = express();\nconst PORT = 3000;\n\n// Middleware\napp.use(express.json());\napp.use(express.static('public'));\n\n// Routes\napp.use('/api', testRoutes);\n\n// Start server\napp.listen(PORT, () => {\n  console.log(`Server running on http://localhost:${PORT}`);\n});\n\n// Connect to MongoDB\nmongoose.connect('mongodb://localhost:27017/testreviewdb', {\n  useNewUrlParser: true,\n  useUnifiedTopology: true,\n});\n\nconst db = mongoose.connection;\ndb.on('error', console.error.bind(console, 'MongoDB connection error:'));\ndb.once('open', () => {\n  console.log('Connected to MongoDB');\n});"}, {"file": "models/Test.js", "path": "models/Test.js", "code": "const mongoose = require('mongoose');\n\nconst testSchema = new mongoose.Schema({\n  project_id: { type: String, required: true },\n  testcode: { type: Object, required: true },\n  status: { type: String, enum: ['Pass', 'Fail', 'Select'], required: true },\n  timestamp: { type: Date, default: Date.now }\n});\n\nmodule.exports = mongoose.model('Test', testSchema);"}, {"file": "routes/testRoutes.js", "path": "routes/testRoutes.js", "code": "const express = require('express');\nconst Test = require('../models/Test');\nconst router = express.Router();\n\n// Get test data by project_id\nrouter.get('/test/:project_id', async (req, res) => {\n  try {\n    const test = await Test.findOne({ project_id: req.params.project_id });\n    if (!test) {\n      return res.status(404).json({ error: 'Test data not found' });\n    }\n    res.json(test);\n  } catch (err) {\n    res.status(500).json({ error: err.message });\n  }\n});\n\n// Update test status\nrouter.post('/test/:project_id/status', async (req, res) => {\n  try {\n    const { status } = req.body;\n    const test = await Test.findOneAndUpdate(\n      { project_id: req.params.project_id },\n      { status },\n      { new: true }\n    );\n    if (!test) {\n      return res.status(404).json({ error: 'Test data not found' });\n    }\n    res.json(test);\n  } catch (err) {\n    res.status(500).json({ error: err.message });\n  }\n});\n\nmodule.exports = router;"}, {"file": "public/index.html", "path": "public/index.html", "code": "<!DOCTYPE html>\n<html lang=\"en\">\n<head>\n  <meta charset=\"UTF-8\">\n  <meta name=\"viewport\" content=\"width=device-width, initial-scale=1.0\">\n  <title>Test Review</title>\n  <link rel=\"stylesheet\" href=\"styles.css\">\n</head>\n<body>\n  <div class=\"container\">\n    <h1>Test Review Page</h1>\n    <div id=\"test-results\"></div>\n  </div>\n  <script src=\"script.js\"></script>\n</body>\n</html>"}, {"file": "public/styles.css", "path": "public/styles.css", "code": "body {\n  font-family: Arial, sans-serif;\n  background-color: #f4f4f4;\n  padding: 20px;\n}\n\n.container {\n  max-width: 800px;\n  margin: 0 auto;\n  background: white;\n  padding: 20px;\n  border-radius: 8px;\n  box-shadow: 0 0 10px rgba(0,0,0,0.1);\n}\n\n.test-item {\n  border: 1px solid #ddd;\n  padding: 15px;\n  margin-bottom: 15px;\n  border-radius: 5px;\n}\n\n.status-buttons {\n  margin-top: 10px;\n}\n\n.status-buttons button {\n  margin-right: 10px;\n  padding: 5px 10px;\n  cursor: pointer;\n}\n\nbutton.pass {\n  background-color: #d4edda;\n  color: #155724;\n}\n\nbutton.fail {\n  background-color: #f8d7da;\n  color: #721c24;\n}\n\nbutton.select {\n  background-color: #fff3cd;\n  color: #856404;\n}"}, {"file": "public/script.js", "path": "public/script.js", "code": "document.addEventListener('DOMContentLoaded', () => {\n  const testResultsDiv = document.getElementById('test-results');\n  const sampleData = {\n    project_id: '3',\n    testcode: {\n      page: 'Home',\n      function: [\n        {\n          function: 'Display Welcome Message',\n          test: 'def test_display_welcome_message(...)',\n          status: 'Select'\n        },\n        {\n          function: 'Navigation Button',\n          test: 'def test_navigation_button(...)',\n          status: 'Select'\n        }\n      ]\n    }\n  };\n\n  // Render test results\n  function renderTestResults(data) {\n    testResultsDiv.innerHTML = '';\n    \n    data.testcode.function.forEach((item, index) => {\n      const div = document.createElement('div');\n      div.className = 'test-item';\n      div.innerHTML = `\n        <h3>${item.function}</h3>\n        <p><strong>Test:</strong> ${item.test}</p>\n        <div class=\"status-buttons\">\n          <button class=\"pass\" data-index=\"${index}\">Pass</button>\n          <button class=\"fail\" data-index=\"${index}\">Fail</button>\n          <button class=\"select\" data-index=\"${index}\">Select</button>\n        </div>\n      `;\n      testResultsDiv.appendChild(div);\n    });\n  }\n\n  // Handle status button clicks\n  testResultsDiv.addEventListener('click', (e) => {\n    if (e.target.classList.contains('pass') ||\n        e.target.classList.contains('fail') ||\n        e.target.classList.contains('select')) {\n      \n      const index = e.target.getAttribute('data-index');\n      const status = e.target.classList.contains('pass') ? 'Pass' : \n                     e.target.classList.contains('fail') ? 'Fail' : 'Select';\n      \n      // In a real app, this would send a POST request to the server\n      console.log(`Test item ${index} status set to: ${status}`);\n    }\n  });\n\n  renderTestResults(sampleData);\n});"}, {"file": "start.py", "path": "start.py", "code": "import subprocess\n\n# Install dependencies\nsubprocess.run(['npm', 'install', 'express', 'mongoose'], shell=True)\n\n# Start the server\nsubprocess.run(['node', 'app.js'], shell=True)"}], "12": [{"file": "start.py", "path": "start.py", "code": "import subprocess\nsubprocess.run([\"npm\", \"install\", \"express\",\"mongoose\",\"body-parser\",\"ejs\"], shell=True)\nsubprocess.run([\"node\", \"server.js\"], shell=True)"}, {"file": "package.json", "path": "package.json", "code": "{\n  \"name\": \"accounting-system\",\n  \"version\": \"1.0.0\",\n  \"description\": \"Accounting and cashier information management system\",\n  \"main\": \"server.js\",\n  \"scripts\": {\n    \"start\": \"node server.js\"\n  },\n  \"dependencies\": {\n    \"express\": \"^4.18.2\",\n    \"mongoose\": \"^7.6.3\",\n    \"body-parser\": \"^1.20.2\",\n    \"ejs\": \"^3.1.9\"\n  }\n}"}], "13": [{"file": "app.js", "path": "server/app.js", "code": "const express = require('express');\nconst mongoose = require('mongoose');\nconst customerRoutes = require('./routes/customer');\nconst productRoutes = require('./routes/product');\nconst purchaseRoutes = require('./routes/purchase');\n\nconst app = express();\nconst PORT = 3000;\n\nmongoose.connect('mongodb://localhost:27017/crm', {\n  useNewUrlParser: true,\n  useUnifiedTopology: true,\n});\n\napp.use(express.json());\napp.use('/api/customers', customerRoutes);\napp.use('/api/products', productRoutes);\napp.use('/api/purchases', purchaseRoutes);\n\napp.listen(PORT, () => {\n  console.log(`Server running on http://localhost:${PORT}`);\n});"}, {"file": "models/Customer.js", "path": "server/models/Customer.js", "code": "const mongoose = require('mongoose');\n\nconst customerSchema = new mongoose.Schema({\n  name: { type: String, required: true },\n  birthday: { type: Date, required: true },\n  age: { type: Number, required: true },\n  sex: { type: String, required: true },\n  company: { type: String, required: true },\n  phoneNumber: { type: String, required: true },\n  preferredProducts: [{ type: mongoose.Schema.Types.ObjectId, ref: 'Product' }],\n});\n\nmodule.exports = mongoose.model('Customer', customerSchema);"}, {"file": "models/Product.js", "path": "server/models/Product.js", "code": "const mongoose = require('mongoose');\n\nconst productSchema = new mongoose.Schema({\n  name: { type: String, required: true },\n  category: { type: String, required: true },\n  recommendedPrice: { type: Number, required: true },\n});\n\nmodule.exports = mongoose.model('Product', productSchema);"}, {"file": "models/Purchase.js", "path": "server/models/Purchase.js", "code": "const mongoose = require('mongoose');\n\nconst purchaseSchema = new mongoose.Schema({\n  datetime: { type: Date, required: true },\n  product: { type: mongoose.Schema.Types.ObjectId, ref: 'Product', required: true },\n  customer: { type: mongoose.Schema.Types.ObjectId, ref: 'Customer', required: true },\n  quantity: { type: Number, required: true },\n  amount: { type: Number, required: true },\n});\n\nmodule.exports = mongoose.model('Purchase', purchaseSchema);"}, {"file": "routes/customer.js", "path": "server/routes/customer.js", "code": "const express = require('express');\nconst Customer = require('../models/Customer');\nconst router = express.Router();\n\nrouter.post('/', async (req, res) => {\n  try {\n    const customer = new Customer(req.body);\n    await customer.save();\n    res.status(201).json(customer);\n  } catch (err) {\n    res.status(400).json({ error: err.message });\n  }\n});\n\nrouter.get('/', async (req, res) => {\n  try {\n    const customers = await Customer.find();\n    res.json(customers);\n  } catch (err) {\n    res.status(500).json({ error: err.message });\n  }\n});\n\nmodule.exports = router;"}, {"file": "routes/product.js", "path": "server/routes/product.js", "code": "const express = require('express');\nconst Product = require('../models/Product');\nconst router = express.Router();\n\nrouter.post('/', async (req, res) => {\n  try {\n    const product = new Product(req.body);\n    await product.save();\n    res.status(201).json(product);\n  } catch (err) {\n    res.status(400).json({ error: err.message });\n  }\n});\n\nrouter.get('/', async (req, res) => {\n  try {\n    const products = await Product.find();\n    res.json(products);\n  } catch (err) {\n    res.status(500).json({ error: err.message });\n  }\n});\n\nmodule.exports = router;"}, {"file": "routes/purchase.js", "path": "server/routes/purchase.js", "code": "const express = require('express');\nconst Purchase = require('../models/Purchase');\nconst router = express.Router();\n\nrouter.post('/', async (req, res) => {\n  try {\n    const purchase = new Purchase(req.body);\n    await purchase.save();\n    res.status(201).json(purchase);\n  } catch (err) {\n    res.status(400).json({ error: err.message });\n  }\n});\n\nrouter.get('/', async (req, res) => {\n  try {\n    const purchases = await Purchase.find().populate('product customer');\n    res.json(purchases);\n  } catch (err) {\n    res.status(500).json({ error: err.message });\n  }\n});\n\nmodule.exports = router;"}, {"file": "public/index.html", "path": "public/index.html", "code": "<!DOCTYPE html>\n<html>\n<head>\n  <title>CRM System</title>\n  <link rel=\"stylesheet\" type=\"text/css\" href=\"styles.css\">\n</head>\n<body>\n  <div id=\"container\">\n    <h1>Customer Management</h1>\n    <form id=\"customerForm\">\n      <input type=\"text\" id=\"name\" placeholder=\"Name\" required>\n      <input type=\"date\" id=\"birthday\" required>\n      <input type=\"number\" id=\"age\" required>\n      <input type=\"text\" id=\"sex\" placeholder=\"Sex\" required>\n      <input type=\"text\" id=\"company\" placeholder=\"Company\" required>\n      <input type=\"tel\" id=\"phone\" placeholder=\"Phone\" required>\n      <button type=\"submit\">Add Customer</button>\n    </form>\n\n    <h2>Products</h2>\n    <form id=\"productForm\">\n      <input type=\"text\" id=\"productName\" placeholder=\"Product Name\" required>\n      <input type=\"text\" id=\"category\" placeholder=\"Category\" required>\n      <input type=\"number\" id=\"price\" placeholder=\"Price\" required>\n      <button type=\"submit\">Add Product</button>\n    </form>\n\n    <h2>Purchases</h2>\n    <form id=\"purchaseForm\">\n      <input type=\"date\" id=\"purchaseDate\" required>\n      <select id=\"productSelect\"></select>\n      <select id=\"customerSelect\"></select>\n      <input type=\"number\" id=\"quantity\" placeholder=\"Quantity\" required>\n      <input type=\"number\" id=\"amount\" placeholder=\"Amount\" required>\n      <button type=\"submit\">Add Purchase</button>\n    </form>\n\n    <div id=\"dashboard\">\n      <h3>Sales Analysis</h3>\n      <canvas id=\"salesChart\"></canvas>\n    </div>\n  </div>\n  <script src=\"script.js\"></script>\n</body>\n</html>"}, {"file": "public/styles.css", "path": "public/styles.css", "code": "body {\n  font-family: Arial, sans-serif;\n  margin: 20px;\n}\n\n#container {\n  max-width: 800px;\n  margin: auto;\n}\n\nform {\n  margin-bottom: 20px;\n}\n\ninput, select, button {\n  margin: 5px 0;\n  padding: 8px;\n  width: 100%;\n}\n\n#dashboard {\n  margin-top: 40px;\n}\n\ncanvas {\n  width: 100%;\n  height: 400px;\n}"}, {"file": "public/script.js", "path": "public/script.js", "code": "document.addEventListener('DOMContentLoaded', () => {\n  const customerForm = document.getElementById('customerForm');\n  const productForm = document.getElementById('productForm');\n  const purchaseForm = document.getElementById('purchaseForm');\n  const productSelect = document.getElementById('productSelect');\n  const customerSelect = document.getElementById('customerSelect');\n  const salesChart = document.getElementById('salesChart');\n\n  // Fetch customers and populate selects\n  async function fetchCustomers() {\n    const res = await fetch('/api/customers');\n    const customers = await res.json();\n    customers.forEach(customer => {\n      const option = document.createElement('option');\n      option.value = customer._id;\n      option.textContent = customer.name;\n      customerSelect.appendChild(option);\n    });\n  }\n\n  // Fetch products and populate selects\n  async function fetchProducts() {\n    const res = await fetch('/api/products');\n    const products = await res.json();\n    products.forEach(product => {\n      const option = document.createElement('option');\n      option.value = product._id;\n      option.textContent = product.name;\n      productSelect.appendChild(option);\n    });\n  }\n\n  // Add customer\n  customerForm.addEventListener('submit', async (e) => {\n    e.preventDefault();\n    const customer = {\n      name: document.getElementById('name').value,\n      birthday: document.getElementById('birthday').value,\n      age: parseInt(document.getElementById('age').value),\n      sex: document.getElementById('sex').value,\n      company: document.getElementById('company').value,\n      phoneNumber: document.getElementById('phone').value\n    };\n    await fetch('/api/customers', {\n      method: 'POST',\n      headers: { 'Content-Type': 'application/json' },\n      body: JSON.stringify(customer)\n    });\n    customerForm.reset();\n  });\n\n  // Add product\n  productForm.addEventListener('submit', async (e) => {\n    e.preventDefault();\n    const product = {\n      name: document.getElementById('productName').value,\n      category: document.getElementById('category').value,\n      recommendedPrice: parseFloat(document.getElementById('price').value)\n    };\n    await fetch('/api/products', {\n      method: 'POST',\n      headers: { 'Content-Type': 'application/json' },\n      body: JSON.stringify(product)\n    });\n    productForm.reset();\n  });\n\n  // Add purchase\n  purchaseForm.addEventListener('submit', async (e) => {\n    e.preventDefault();\n    const purchase = {\n      datetime: document.getElementById('purchaseDate').value,\n      product: productSelect.value,\n      customer: customerSelect.value,\n      quantity: parseInt(document.getElementById('quantity').value),\n      amount: parseFloat(document.getElementById('amount').value)\n    };\n    await fetch('/api/purchases', {\n      method: 'POST',\n      headers: { 'Content-Type': 'application/json' },\n      body: JSON.stringify(purchase)\n    });\n    purchaseForm.reset();\n  });\n\n  // Initialize selects\n  fetchCustomers();\n  fetchProducts();\n\n  // Sales chart\n  async function loadSalesChart() {\n    const res = await fetch('/api/purchases');\n    const purchases = await res.json();\n    const productSales = {};\n    purchases.forEach(purchase => {\n      productSales[purchase.product.name] = (productSales[purchase.product.name] || 0) + purchase.amount;\n    });\n\n    const ctx = salesChart.getContext('2d');\n    new Chart(ctx, {\n      type: 'bar',\n      data: {\n        labels: Object.keys(productSales),\n        datasets: [{\n          label: 'Total Sales by Product',\n          data: Object.values(productSales),\n          backgroundColor: 'rgba(75, 192, 192, 0.6)'\n        }]\n      },\n      options: {\n        scales: {\n          y: {\n            beginAtZero: true\n          }\n        }\n      }\n    });\n  }\n\n  loadSalesChart();\n});"}, {"file": "start.py", "path": "start.py", "code": "import subprocess\n\nsubprocess.run(['npm', 'install', 'express', 'mongoose', 'body-parser', 'chart.js'], shell=True)\nsubprocess.run(['node', 'server/app.js'], shell=True)"}], "15": [{"file": "server.js", "path": "server.js", "code": "const express = require('express');\nconst path = require('path');\n\nconst app = express();\nconst PORT = 3000;\n\n// Serve static files from the 'public' directory\napp.use(express.static(path.join(__dirname, 'public')));\n\n// Route for the main page\napp.get('/', (req, res) => {\n  res.sendFile(path.join(__dirname, 'public', 'index.html'));\n});\n\n// Route for the helloworld page\napp.get('/helloworld', (req, res) => {\n  res.sendFile(path.join(__dirname, 'public', 'helloworld.html'));\n});\n\napp.listen(PORT, () => {\n  console.log(`Server is running on http://localhost:${PORT}`);\n});"}, {"file": "index.html", "path": "public/index.html", "code": "<!DOCTYPE html>\n<html lang=\"en\">\n<head>\n  <meta charset=\"UTF-8\">\n  <meta name=\"viewport\" content=\"width=device-width, initial-scale=1.0\">\n  <title>Main Page</title>\n</head>\n<body>\n  <div class=\"container\" id=\"main-container\">\n    <button class=\"jump-button\" id=\"jump-btn\">Jump to Hello World</button>\n  </div>\n</body>\n</html>"}, {"file": "helloworld.html", "path": "public/helloworld.html", "code": "<!DOCTYPE html>\n<html lang=\"en\">\n<head>\n  <meta charset=\"UTF-8\">\n  <meta name=\"viewport\" content=\"width=device-width, initial-scale=1.0\">\n  <title>Hello World</title>\n</head>\n<body>\n  <div class=\"content\" id=\"hello-container\">\n    <h1 class=\"greeting\">Hello, World!</h1>\n  </div>\n</body>\n</html>"}, {"file": "start.py", "path": "start.py", "code": "import subprocess\n\n# Install dependencies\nsubprocess.run(\"npm install express\", shell=True, check=True)\n\n# Start the Node.js server\nsubprocess.run(\"node server.js\", shell=True)"}], "16": [{"file": "start.py", "path": "start.py", "code": "import subprocess\n\nsubprocess.run([\"npm\", \"install\", \"xlsx\"], shell=True)\nsubprocess.run([\"node\", \"index.js\"], shell=True)"}, {"file": "package.json", "path": "package.json", "code": "{\n  \"name\": \"excel-processor\",\n  \"version\": \"1.0.0\",\n  \"description\": \"\",\n  \"main\": \"index.js\",\n  \"scripts\": {\n    \"start\": \"node index.js\"\n  },\n  \"keywords\": [],\n  \"author\": \"\",\n  \"license\": \"ISC\",\n  \"dependencies\": {\n    \"xlsx\": \"^4.21.0\"\n  }\n}"}, {"file": "index.js", "path": "index.js", "code": "const XLSX = require('xlsx');\n\n// Read input file\nconst workbook = XLSX.readFile('Spring Semester Subjects.xlsx');\nconst sheet = workbook.Sheets[workbook.SheetNames[0]];\n\n// Parse data\nconst data = XLSX.utils.sheet_to_json(sheet);\n\n// Create 2D table structure\nconst weekdays = ['Monday', 'Tuesday', 'Wednesday', 'Thursday', 'Friday'];\nconst periods = ['First period', 'Second period', 'Third period', 'Fourth period'];\n\nconst table = {};\nweekdays.forEach(weekday => {\n  table[weekday] = {};\n  periods.forEach(period => {\n    table[weekday][period] = '';\n  });\n});\n\n// Populate table data\ndata.forEach(item => {\n  if (weekdays.includes(item.Weekday) && periods.includes(item.Time)) {\n    table[item.Weekday][item.Time] = item.Name;\n  }\n});\n\n// Convert to 2D array for output\nconst outputData = [];\noutputData.push(['', ...periods]);\nweekdays.forEach(weekday => {\n  const row = [weekday];\n  periods.forEach(period => {\n    row.push(table[weekday][period]);\n  });\n  outputData.push(row);\n});\n\n// Write to output file\nconst outputWorkbook = XLSX.utils.book_new();\nconst outputSheet = XLSX.utils.aoa_to_sheet(outputData);\nXLSX.utils.book_append_sheet(outputWorkbook, outputSheet, 'Subject Table');\nXLSX.writeFile(outputWorkbook, 'output.xlsx');\n\nconsole.log('Processing complete. Output saved as output.xlsx');"}, {"file": ".gitignore", "path": ".gitignore", "code": "node_modules/\noutput.xlsx"}], "18": [{"file": "start.py", "path": "start.py", "code": "import subprocess\nsubprocess.run(['node', 'game.js'], shell=True)"}, {"file": "package.json", "path": "package.json", "code": "{\n  \"name\": \"bashcrawl\",\n  \"version\": \"1.0.0\",\n  \"scripts\": {\n    \"start\": \"node game.js\"\n  },\n  \"dependencies\": {}\n}"}, {"file": "game.js", "path": "game.js", "code": "const readline = require('readline');\n\nclass Room {\n  constructor(description, exits) {\n    this.description = description;\n    this.exits = exits;\n  }\n}\n\nconst rooms = {\n  'entrance': new Room('You are at the entrance. There is a door to the east.', { 'east': 'hall' }),\n  'hall': new Room('You are in a dimly lit hall. There is a door to the west and north.', { 'west': 'entrance', 'north': 'kitchen' }),\n  'kitchen': new Room('You are in a kitchen with a table and chairs. There is a door to the south.', { 'south': 'hall' })\n};\n\nlet currentRoom = rooms['entrance'];\n\nconst rl = readline.createInterface({\n  input: process.stdin,\n  output: process.stdout\n});\n\nrl.on('line', (input) => {\n  const [command, direction] = input.trim().split(' ');\n  \n  if (command.toLowerCase() === 'go' && direction in currentRoom.exits) {\n    currentRoom = rooms[currentRoom.exits[direction]];\n    console.log(`\\n${currentRoom.description}`);\n    console.log('Available directions:', Object.keys(currentRoom.exits).join(', '));\n  } else {\n    console.log('Invalid command or direction. Try again.\\n');\n  }\n});\n\nconsole.log(`\\n${currentRoom.description}`);\nconsole.log('Available directions:', Object.keys(currentRoom.exits).join(', '));"}], "19": [{"file": "start.py", "path": "start.py", "code": "import subprocess\nsubprocess.run([\"npm\", \"install\", \"express\", \"csv-parser\"], shell=True)\nsubprocess.run([\"node\", \"server.js\"], shell=True)"}, {"file": "package.json", "path": "package.json", "code": "{\n  \"name\": \"deathlist-histogram\",\n  \"version\": \"1.0.0\",\n  \"description\": \"\",\n  \"main\": \"server.js\",\n  \"scripts\": {\n    \"start\": \"node server.js\"\n  },\n  \"dependencies\": {\n    \"express\": \"^4.18.2\",\n    \"csv-parser\": \"^3.1.1\"\n  }\n}"}]}