{"1": {"initiate_commands": [["manage.py", "makemigrations"], ["manage.py", "migrate"], ["manage.py", "runserver"]], "requirements": ["Django>=4.2"]}, "2": {"initiate_commands": [["manage.py", "makemigrations"], ["manage.py", "migrate"], ["manage.py", "runserver"]], "requirements": ["Django>=4.2"]}, "3": {"initiate_commands": [["manage.py", "makemigrations"], ["manage.py", "migrate"], ["python", "-m", "http.server"]], "requirements": ["Django>=4.2"]}, "4": {"initiate_commands": [["manage.py", "makemigrations"], ["manage.py", "migrate"], ["manage.py", "runserver"]], "requirements": ["Django>=4.0", "qrcode"]}, "5": {"initiate_commands": [["manage.py", "makemigrations"], ["manage.py", "migrate"], ["python", "-m", "http.server"]], "requirements": ["Django>=4.2", "markdown2"]}, "6": {"initiate_commands": [["manage.py", "makemigrations"], ["manage.py", "migrate"], ["manage.py", "runserver"]], "requirements": ["Django>=4.2"]}, "7": {"initiate_commands": [["manage.py", "makemigrations"], ["manage.py", "migrate"], ["manage.py", "runserver"]], "requirements": ["Django>=4.2,<5"]}, "8": {"initiate_commands": [["manage.py", "makemigrations"], ["manage.py", "migrate"], ["manage.py", "runserver"]], "requirements": ["Django>=4.2"]}, "9": {"initiate_commands": [["manage.py", "makemigrations"], ["manage.py", "migrate"], ["manage.py", "runserver"]], "requirements": ["Django>=4.2"]}, "10": {"initiate_commands": [["manage.py", "makemigrations"], ["manage.py", "migrate"], ["manage.py", "runserver"]], "requirements": ["Django"]}, "11": {"initiate_commands": [["manage.py", "makemigrations"], ["manage.py", "migrate"], ["manage.py", "runserver"]], "requirements": ["Django>=4.0"]}, "12": {"initiate_commands": [["manage.py", "makemigrations"], ["manage.py", "migrate"], ["manage.py", "runserver"]], "requirements": ["Django>=4.2,<5.0"]}, "13": "```json\n{\n  \"initiate_commands\": [\n    [\"manage.py\", \"makemigrations\"],\n    [\"manage.py\", \"migrate\"],\n    [\"python\", \"-m\", \"venv\", \"env\"],\n    [\"source\", \"env/bin/activate\"], // For Unix or MacOS\n    [\"env\\\\\\\\Scripts\\\\\\\\activate.bat\"], // For Windows\n    [\"pip\", \"install\", \"Django\"]\n  ],\n  \"requirements\": [\n    \"Django\"\n  ]\n}\n```\n\n**Homepage URL:**\n\nThe homepage URL for this Django project is `http://127.0.0.1:8000/` after running the server with `python manage.py runserver`.", "14": {"initiate_commands": [["manage.py", "makemigrations"], ["manage.py", "migrate"], ["manage.py", "runserver"]], "requirements": ["Django>=4.2"]}, "15": {"initiate_commands": [["manage.py", "makemigrations"], ["manage.py", "migrate"], ["python", "-m", "http.server"]], "requirements": ["Django>=4.2"]}, "18": {"initiate_commands": [["python", "-m", "http.server"], ["open", "http://localhost:8000/src/index.html"]], "requirements": []}, "20": {"initiate_commands": [["manage.py", "makemigrations"], ["manage.py", "migrate"], ["manage.py", "createsuperuser"], ["python", "-m", "http.server"]], "requirements": ["Django>=4.0,<5.0"]}}